sqsi/__init__.py
sqsi/queue_iterator.py
sqsi-0.1.9.dist-info/licenses/LICENSE
sqsi-0.1.9.dist-info/METADATA
sqsi-0.1.9.dist-info/WHEEL
sqsi-0.1.9.dist-info/top_level.txt
sqsi-0.1.9.dist-info/RECORD
