Metadata-Version: 2.4
Name: sqsi
Version: 0.1.9
Summary: Async Iterators for SQS Queues
Author-email: Robert Howe <rc@rchowe.com>
License: MIT
Project-URL: Homepage, https://github.com/rchowe/sqsi
Project-URL: Issues, https://github.com/rchowe/sqsi/issues
Requires-Python: >3.10.0
License-File: LICENSE
Requires-Dist: aiobotocore>=2.23.1
Requires-Dist: types-aiobotocore[sqs]>=2.23.1
Dynamic: license-file
